{
  "kind": "collectionType",
  "collectionName": "tasks",
  "info": {
    "singularName": "task",
    "pluralName": "tasks",
    "displayName": "Task"
  },
  "options": {
    "draftAndPublish": true
  },
  "pluginOptions": {
    "i18n": {
      "localized": true
    }
  },
  "attributes": {
    "nameTask": {
      "type": "string",
      "pluginOptions": {
        "i18n": {
          "localized": true
        }
      }
    },
    "idTask": {
      "type": "string",
      "pluginOptions": {
        "i18n": {
          "localized": true
        }
      }
    },
    "descriptionShort": {
      "type": "string",
      "pluginOptions": {
        "i18n": {
          "localized": true
        }
      }
    },
    "urgency": {
      "type": "integer",
      "pluginOptions": {
        "i18n": {
          "localized": true
        }
      }
    },
    "audiences": {
      "type": "relation",
      "relation": "oneToMany",
      "target": "api::audience.audience",
      "mappedBy": "task"
    },
    "missionTags": {
      "type": "relation",
      "relation": "oneToMany",
      "target": "api::mission-tag.mission-tag",
      "mappedBy": "MissionTags"
    },
    "linkedArticle": {
      "type": "relation",
      "relation": "oneToOne",
      "target": "api::knowledge-article.knowledge-article"
    },
    "categories": {
      "type": "relation",
      "relation": "oneToMany",
      "target": "api::category.category",
      "mappedBy": "tasks"
    },
    "locations": {
      "type": "relation",
      "relation": "oneToMany",
      "target": "api::location.location",
      "mappedBy": "tasks"
    },
    "depends_ons": {
      "type": "relation",
      "relation": "oneToMany",
      "target": "api::task.task"
    }
  }
}
